[
  {
    "id": "1",
    "order": 1,
    "name": "Legs",
    "userId": "1",
    "exercises": [
      {
        "order": 1,
        "id": "1000",
        "name": "band single leg reverse calf raise"
      },
      { "order": 2, "id": "1001", "name": "band single leg split squat" }
    ]
  },
  {
    "id": "2",
    "userId": "1",
    "order": 2,
    "name": "Core",
    "exercises": [
      { "order": 1, "id": "0545", "name": "kettlebell plyo push-up" },
      { "order": 2, "id": "1761", "name": "hanging oblique knee raise" },
      { "order": 3, "id": "0473", "name": "hanging pike" }
    ]
  }
]
